structuralpy/__init__.py
structuralpy/rc_beam.py
structuralpy-0.0.4.dist-info/LICENSE
structuralpy-0.0.4.dist-info/METADATA
structuralpy-0.0.4.dist-info/WHEEL
structuralpy-0.0.4.dist-info/top_level.txt
structuralpy-0.0.4.dist-info/RECORD
