Metadata-Version: 2.1
Name: structuralpy
Version: 0.0.4
Summary: A library for analysis and design of structures based on NSCP 2015.
Author: Jaydee Lucero
Author-email: jaydee.lucero@gmail.com
License: MIT
Requires-Python: >=3.7
License-File: LICENSE
Requires-Dist: pytest
Requires-Dist: sympy
